{
  "add_edit_model": {
    "vendor": {
      "This field may not be blank.": "Please enter a vendor",
      "Ensure this field has no more than 30 characters.": "Please enter a vendor no longer than 30 characters"
    },
    "model_number": {
      "This field may not be blank.": "Please enter a model number",
      "Ensure this field has no more than 40 characters.": "Please enter a model number no longer than 40 characters"
    },
    "description": {
      "This field may not be blank.": "Please enter a description",
      "Ensure this field has no more than 100 characters.": "Please enter a description no longer than 100 characters"
    },
    "comment": {
      "Ensure this field has no more than 2000 characters.": "Please enter a comment no longer than 2000 characters"
    },
    "calibration_frequency": {
      "A valid integer is required.": "Please enter an integer for the Calibration Frequency",
      "Ensure this value is less than or equal to 3653.": "Please enter a value no longer than 3653 days (10 years) for the Calibration Frequency",
      "Ensure this value is greater than or equal to 0.": "Please enter a value greater than 0 for the Calibration Frequency"
    },
    "non_field_errors": {
      "The fields vendor, model_number must make a unique set.": "This model already exists"
    }
  },
  "delete_model": {
    "delete_error": {
      "Cannot delete model with instrument instances.": "Failed: Cannot delete a model with existing instruments"
    }
  }
}
